hmtredishelp/__init__.py
hmtredishelp/redis_dump_utils.py
hmtredishelp-0.1.19.dist-info/DESCRIPTION.rst
hmtredishelp-0.1.19.dist-info/METADATA
hmtredishelp-0.1.19.dist-info/RECORD
hmtredishelp-0.1.19.dist-info/WHEEL
hmtredishelp-0.1.19.dist-info/metadata.json
hmtredishelp-0.1.19.dist-info/top_level.txt
