Metadata-Version: 2.0
Name: hmtredishelp
Version: 0.1.19
Summary: A set of tools we use to easily access redis
Home-page: https://github.com/IntuitionMachines/redis-tools
Author: Intuition Machines
Author-email: dev@intuitionmachines.com
License: MIT
Platform: UNKNOWN
Requires-Dist: redis
